xa_izipy/__init__.py
xa_izipy/iziinfo.py
xa_izipy/tools/__init__.py
xa_izipy/tools/tools.py
xa_izipy-0.0.5.dist-info/METADATA
xa_izipy-0.0.5.dist-info/WHEEL
xa_izipy-0.0.5.dist-info/top_level.txt
xa_izipy-0.0.5.dist-info/RECORD
