Metadata-Version: 2.4
Name: xa_izipy
Version: 0.0.5
Summary: Упрощает какие-то функции
Author: Rigew
Classifier: Programming Language :: Python :: 3
Classifier: Operating System :: OS Independent
Requires-Python: >=3.6
Requires-Dist: psutil
